library_gpt4all/__init__.py
library_gpt4all/main.py
library_gpt4all-0.1.0.dist-info/METADATA
library_gpt4all-0.1.0.dist-info/WHEEL
library_gpt4all-0.1.0.dist-info/entry_points.txt
library_gpt4all-0.1.0.dist-info/top_level.txt
library_gpt4all-0.1.0.dist-info/RECORD
