Metadata-Version: 2.1
Name: library_gpt4all
Version: 0.1.0
Summary: Библиотека для запуска графического интерфейса с нейросетью GPT4All
Home-page: https://github.com/ваш_username/ваш_репозиторий
Author: maga22maga44
Author-email: maga22maga44@gmail.com
License: MIT
Keywords: gpt4all customtkinter gui neural-network
Classifier: Programming Language :: Python :: 3
Classifier: License :: OSI Approved :: MIT License
Classifier: Operating System :: OS Independent
Classifier: Development Status :: 3 - Alpha
Classifier: Intended Audience :: Developers
Classifier: Topic :: Software Development :: Libraries :: Python Modules
Requires-Python: >=3.6
Requires-Dist: customtkinter
Requires-Dist: gpt4all
